odoo/addons/automation_oca/README.rst
odoo/addons/automation_oca/__init__.py
odoo/addons/automation_oca/__manifest__.py
odoo/addons/automation_oca/controllers/__init__.py
odoo/addons/automation_oca/controllers/main.py
odoo/addons/automation_oca/data/cron.xml
odoo/addons/automation_oca/demo/demo.xml
odoo/addons/automation_oca/i18n/automation_oca.pot
odoo/addons/automation_oca/i18n/es.po
odoo/addons/automation_oca/i18n/fr.po
odoo/addons/automation_oca/i18n/it.po
odoo/addons/automation_oca/models/__init__.py
odoo/addons/automation_oca/models/automation_configuration.py
odoo/addons/automation_oca/models/automation_configuration_step.py
odoo/addons/automation_oca/models/automation_filter.py
odoo/addons/automation_oca/models/automation_record.py
odoo/addons/automation_oca/models/automation_record_step.py
odoo/addons/automation_oca/models/automation_tag.py
odoo/addons/automation_oca/models/link_tracker.py
odoo/addons/automation_oca/models/mail_activity.py
odoo/addons/automation_oca/models/mail_mail.py
odoo/addons/automation_oca/models/mail_thread.py
odoo/addons/automation_oca/readme/CONTRIBUTORS.md
odoo/addons/automation_oca/readme/CREDITS.md
odoo/addons/automation_oca/readme/DESCRIPTION.md
odoo/addons/automation_oca/readme/USAGE.md
odoo/addons/automation_oca/security/ir.model.access.csv
odoo/addons/automation_oca/security/security.xml
odoo/addons/automation_oca/static/description/configuration.png
odoo/addons/automation_oca/static/description/icon.png
odoo/addons/automation_oca/static/description/icon.svg
odoo/addons/automation_oca/static/description/index.html
odoo/addons/automation_oca/static/src/fields/automation_activity/automation_activity.esm.js
odoo/addons/automation_oca/static/src/fields/automation_graph/automation_graph.esm.js
odoo/addons/automation_oca/static/src/fields/automation_graph/automation_graph.xml
odoo/addons/automation_oca/static/src/views/automation_kanban/automation_kanban.scss
odoo_addon_automation_oca-18.0.1.0.2.dist-info/METADATA
odoo_addon_automation_oca-18.0.1.0.2.dist-info/WHEEL
odoo_addon_automation_oca-18.0.1.0.2.dist-info/top_level.txt
odoo_addon_automation_oca-18.0.1.0.2.dist-info/RECORD
